MANIFEST.in
README.rst
setup.py
mset/__init__.py
mset.egg-info/PKG-INFO
mset.egg-info/SOURCES.txt
mset.egg-info/dependency_links.txt
mset.egg-info/top_level.txt