Metadata-Version: 1.1
Name: mset
Version: 3.5.3
Summary: A no-op version of the runtime python library included in Marmoset Toolbag.
Home-page: https://marmoset.co
Author: Marmoset LLC
Author-email: support@marmoset.co
License: MIT
Download-URL: https://marmoset.co/toolbag/
Keywords: mset,marmoset,toolbag,hexels
Platform: ANY
Classifier: Topic :: Documentation
Classifier: Topic :: Software Development :: Documentation
Classifier: Development Status :: 3 - Alpha
Classifier: Intended Audience :: Developers
Classifier: Operating System :: OS Independent
Classifier: Programming Language :: Python :: 2
Classifier: Programming Language :: Python :: 2.7
Classifier: Programming Language :: Python :: 3
Classifier: Programming Language :: Python :: 3.4
Classifier: Programming Language :: Python :: 3.5
Classifier: Programming Language :: Python :: 3.6
